redis_semaphore_async/__init__.py
redis_semaphore_async/main.py
redis_semaphore_async-0.0.4.dist-info/LICENSE
redis_semaphore_async-0.0.4.dist-info/METADATA
redis_semaphore_async-0.0.4.dist-info/WHEEL
redis_semaphore_async-0.0.4.dist-info/top_level.txt
redis_semaphore_async-0.0.4.dist-info/RECORD
