Metadata-Version: 2.2
Name: redis_semaphore_async
Version: 0.0.4
Summary: Redis Semaphore Async is a Python library that provides an asynchronous semaphore implementation using Redis as the backend.
Author-email: Kamal Raj K <kamalraj97@gmail.com>
Project-URL: Homepage, https://github.com/kamalkraj/Redis-Semaphore-Async
Project-URL: Issues, https://github.com/kamalkraj/Redis-Semaphore-Async/issues
Classifier: Programming Language :: Python :: 3
Classifier: Operating System :: OS Independent
Classifier: License :: OSI Approved :: Apache Software License
Requires-Python: >=3.10
License-File: LICENSE
Requires-Dist: redis[hiredis]==5.2.1
Provides-Extra: dev
Requires-Dist: black==25.1.0; extra == "dev"
Requires-Dist: isort==6.0.1; extra == "dev"
Requires-Dist: flake8==7.1.2; extra == "dev"
